ipfml/__init__.py
ipfml/exceptions.py
ipfml/metrics.py
ipfml/utils.py
ipfml/filters/__init__.py
ipfml/filters/convolution.py
ipfml/filters/kernels.py
ipfml/filters/noise.py
ipfml/iqa/__init__.py
ipfml/iqa/fr.py
ipfml/processing/__init__.py
ipfml/processing/compression.py
ipfml/processing/movement.py
ipfml/processing/reconstruction.py
ipfml/processing/segmentation.py
ipfml/processing/transform.py
ipfml-1.0.5.dist-info/LICENSE
ipfml-1.0.5.dist-info/METADATA
ipfml-1.0.5.dist-info/WHEEL
ipfml-1.0.5.dist-info/top_level.txt
ipfml-1.0.5.dist-info/RECORD
