Metadata-Version: 2.1
Name: ipfml
Version: 1.0.5
Summary: Image Processing For Machine Learning
Home-page: https://github.com/prise-3d/ipfml
Author: Jérôme BUISINE
Author-email: jerome.buisine@univ-littoral.fr
License: MIT
Platform: UNKNOWN
Classifier: Development Status :: 4 - Beta
Classifier: License :: OSI Approved :: MIT License
Classifier: Programming Language :: Python :: 3.6
Classifier: Topic :: Scientific/Engineering :: Artificial Intelligence
Requires-Dist: numpy
Requires-Dist: Pillow
Requires-Dist: sklearn
Requires-Dist: scikit-image
Requires-Dist: scipy
Requires-Dist: opencv-python
